models/__init__.py
models/agent_endpoint.py
models/agent_endpoint_py3.py
models/connection_contract.py
models/connection_contract_py3.py
models/credential_contract.py
models/credential_contract_py3.py
models/provisioning_info.py
models/provisioning_info_py3.py
models/verification_contract.py
models/verification_contract_py3.py
models/wallet_contract.py
models/wallet_contract_py3.py
models/wallet_info.py
models/wallet_info_py3.py
models/wallet_parameters.py
models/wallet_parameters_py3.py
custodian_streetcred_id-0.0.1.dist-info/LICENSE
custodian_streetcred_id-0.0.1.dist-info/METADATA
custodian_streetcred_id-0.0.1.dist-info/WHEEL
custodian_streetcred_id-0.0.1.dist-info/top_level.txt
custodian_streetcred_id-0.0.1.dist-info/RECORD
